{
  "legislative_session": "136",
  "identifier": "HB 267",
  "title": "Regards creation, display of veterans benefit and services poster",
  "from_organization": "~{\"classification\": \"lower\"}",
  "classification": [
    "bill"
  ],
  "subject": [
    "Commerce",
    "Employment",
    "Military and Veterans"
  ],
  "abstracts": [],
  "other_titles": [
    {
      "note": "long title",
      "title": "To enact section 4113.13 of the Revised Code regarding the creation and display of a poster containing information on benefits and services for veterans."
    }
  ],
  "other_identifiers": [],
  "actions": [
    {
      "description": "Introduced",
      "date": "2025-05-12",
      "organization_id": "~{\"classification\": \"lower\"}",
      "classification": [
        "introduction"
      ],
      "related_entities": [],
      "_processing": {
        "log_file_created": "2025-10-25T03:39:53Z"
      }
    },
    {
      "description": "Refer to Committee",
      "date": "2025-05-14",
      "organization_id": "~{\"classification\": \"lower\"}",
      "classification": [
        "referral-committee"
      ],
      "related_entities": [
        {
          "name": "House Veterans and Military Development Committee",
          "entity_type": "organization",
          "organization_id": null
        }
      ],
      "_processing": {
        "log_file_created": "2025-10-25T03:39:53Z"
      }
    }
  ],
  "sponsorships": [
    {
      "name": "Lauren McNally",
      "classification": "primary",
      "entity_type": "person",
      "primary": true,
      "person_id": "~{\"name\": \"Lauren McNally\"}",
      "organization_id": null
    },
    {
      "name": "Brian Lampton",
      "classification": "primary",
      "entity_type": "person",
      "primary": true,
      "person_id": "~{\"name\": \"Brian Lampton\"}",
      "organization_id": null
    },
    {
      "name": "Beryl Piccolantonio",
      "classification": "cosponsor",
      "entity_type": "person",
      "primary": false,
      "person_id": "~{\"name\": \"Beryl Piccolantonio\"}",
      "organization_id": null
    },
    {
      "name": "Kellie Deeter",
      "classification": "cosponsor",
      "entity_type": "person",
      "primary": false,
      "person_id": "~{\"name\": \"Kellie Deeter\"}",
      "organization_id": null
    },
    {
      "name": "Sean Brennan",
      "classification": "cosponsor",
      "entity_type": "person",
      "primary": false,
      "person_id": "~{\"name\": \"Sean Brennan\"}",
      "organization_id": null
    },
    {
      "name": "Josh Williams",
      "classification": "cosponsor",
      "entity_type": "person",
      "primary": false,
      "person_id": "~{\"name\": \"Josh Williams\"}",
      "organization_id": null
    },
    {
      "name": "Eric Synenberg",
      "classification": "cosponsor",
      "entity_type": "person",
      "primary": false,
      "person_id": "~{\"name\": \"Eric Synenberg\"}",
      "organization_id": null
    },
    {
      "name": "Veronica Sims",
      "classification": "cosponsor",
      "entity_type": "person",
      "primary": false,
      "person_id": "~{\"name\": \"Veronica Sims\"}",
      "organization_id": null
    },
    {
      "name": "Johnathan Newman",
      "classification": "cosponsor",
      "entity_type": "person",
      "primary": false,
      "person_id": "~{\"name\": \"Johnathan Newman\"}",
      "organization_id": null
    },
    {
      "name": "Phil  Plummer",
      "classification": "cosponsor",
      "entity_type": "person",
      "primary": false,
      "person_id": "~{\"name\": \"Phil  Plummer\"}",
      "organization_id": null
    },
    {
      "name": "Tristan Rader",
      "classification": "cosponsor",
      "entity_type": "person",
      "primary": false,
      "person_id": "~{\"name\": \"Tristan Rader\"}",
      "organization_id": null
    },
    {
      "name": "Derrick Hall, D.",
      "classification": "cosponsor",
      "entity_type": "person",
      "primary": false,
      "person_id": "~{\"name\": \"Derrick Hall, D.\"}",
      "organization_id": null
    },
    {
      "name": "Tex Fischer",
      "classification": "cosponsor",
      "entity_type": "person",
      "primary": false,
      "person_id": "~{\"name\": \"Tex Fischer\"}",
      "organization_id": null
    },
    {
      "name": "C. Russo",
      "classification": "cosponsor",
      "entity_type": "person",
      "primary": false,
      "person_id": "~{\"name\": \"C. Russo\"}",
      "organization_id": null
    }
  ],
  "related_bills": [],
  "versions": [
    {
      "note": "As Introduced",
      "links": [
        {
          "url": "https://search-prod.lis.state.oh.us/solarapi/v1/general_assembly_136/bills/hb267/IN/00/hb267_00_IN?format=pdf",
          "media_type": "application/pdf"
        }
      ],
      "date": "",
      "classification": ""
    }
  ],
  "documents": [],
  "citations": [],
  "sources": [
    {
      "url": "https://www.legislature.ohio.gov/legislation/136/hb267",
      "note": ""
    },
    {
      "url": "https://search-prod.lis.state.oh.us/solarapi/v1/general_assembly_136//bills/hb267/",
      "note": ""
    }
  ],
  "extras": {},
  "jurisdiction": {
    "id": "ocd-jurisdiction/country:us/state:oh/government",
    "name": "Ohio",
    "classification": "state",
    "division_id": "ocd-division/country:us/state:oh"
  },
  "_processing": {
    "logs_latest_update": "2025-10-25T03:39:53Z"
  }
}