{
  "legislative_session": "136",
  "identifier": "HR 248",
  "title": "Honoring Tyjon Cousins as the 2025 National Little Brother of the Year.",
  "from_organization": "~{\"classification\": \"lower\"}",
  "classification": [
    "resolution"
  ],
  "subject": [],
  "abstracts": [],
  "other_titles": [
    {
      "note": "long title",
      "title": "Honoring Tyjon Cousins as the 2025 National Little Brother of the Year."
    }
  ],
  "other_identifiers": [],
  "actions": [
    {
      "description": "Adopted",
      "date": "2025-10-01",
      "organization_id": "~{\"classification\": \"lower\"}",
      "classification": [],
      "related_entities": [
        {
          "name": "House Rules and Reference Committee",
          "entity_type": "organization",
          "organization_id": null
        }
      ],
      "_processing": {
        "log_file_created": "2025-10-25T03:39:53Z"
      }
    }
  ],
  "sponsorships": [
    {
      "name": "Karen Brownlee",
      "classification": "primary",
      "entity_type": "person",
      "primary": true,
      "person_id": "~{\"name\": \"Karen Brownlee\"}",
      "organization_id": null
    },
    {
      "name": "Rachel Baker",
      "classification": "primary",
      "entity_type": "person",
      "primary": true,
      "person_id": "~{\"name\": \"Rachel Baker\"}",
      "organization_id": null
    }
  ],
  "related_bills": [],
  "versions": [
    {
      "note": "As Adopted by the House",
      "links": [
        {
          "url": "https://search-prod.lis.state.oh.us/solarapi/v1/general_assembly_136/resolutions/hr248/AH/01/hr248_01_AH?format=pdf",
          "media_type": "application/pdf"
        }
      ],
      "date": "",
      "classification": ""
    },
    {
      "note": "As Offered",
      "links": [
        {
          "url": "https://search-prod.lis.state.oh.us/solarapi/v1/general_assembly_136/resolutions/hr248/IN/00/hr248_00_IN?format=pdf",
          "media_type": "application/pdf"
        }
      ],
      "date": "",
      "classification": ""
    }
  ],
  "documents": [],
  "citations": [],
  "sources": [
    {
      "url": "https://www.legislature.ohio.gov/legislation/136/hr248",
      "note": ""
    },
    {
      "url": "https://search-prod.lis.state.oh.us/solarapi/v1/general_assembly_136//resolutions/hr248/",
      "note": ""
    }
  ],
  "extras": {},
  "jurisdiction": {
    "id": "ocd-jurisdiction/country:us/state:oh/government",
    "name": "Ohio",
    "classification": "state",
    "division_id": "ocd-division/country:us/state:oh"
  },
  "_processing": {
    "logs_latest_update": "2025-10-25T03:39:53Z",
    "text_extraction_latest_update": "2025-10-25T08:42:15.344780Z"
  }
}