{
  "legislative_session": "136",
  "identifier": "HB 314",
  "title": "Limit certain public record requests; allow contractor response",
  "from_organization": "~{\"classification\": \"lower\"}",
  "classification": [
    "bill"
  ],
  "subject": [
    "Public Records",
    "State and Local Government"
  ],
  "abstracts": [],
  "other_titles": [
    {
      "note": "long title",
      "title": "To amend section 149.43 of the Revised Code to restrict harassing or disruptive public records requests and permit private contractors to respond to voluminous public records requests."
    }
  ],
  "other_identifiers": [],
  "actions": [
    {
      "description": "Introduced",
      "date": "2025-06-03",
      "organization_id": "~{\"classification\": \"lower\"}",
      "classification": [
        "introduction"
      ],
      "related_entities": [],
      "_processing": {
        "log_file_created": "2025-10-25T03:39:53Z"
      }
    },
    {
      "description": "Refer to Committee",
      "date": "2025-06-04",
      "organization_id": "~{\"classification\": \"lower\"}",
      "classification": [
        "referral-committee"
      ],
      "related_entities": [
        {
          "name": "House Judiciary Committee",
          "entity_type": "organization",
          "organization_id": null
        }
      ],
      "_processing": {
        "log_file_created": "2025-10-25T03:39:53Z"
      }
    }
  ],
  "sponsorships": [
    {
      "name": "Dani Isaacsohn",
      "classification": "primary",
      "entity_type": "person",
      "primary": true,
      "person_id": "~{\"name\": \"Dani Isaacsohn\"}",
      "organization_id": null
    },
    {
      "name": "Sharon Ray",
      "classification": "primary",
      "entity_type": "person",
      "primary": true,
      "person_id": "~{\"name\": \"Sharon Ray\"}",
      "organization_id": null
    }
  ],
  "related_bills": [],
  "versions": [
    {
      "note": "As Introduced",
      "links": [
        {
          "url": "https://search-prod.lis.state.oh.us/solarapi/v1/general_assembly_136/bills/hb314/IN/00/hb314_00_IN?format=pdf",
          "media_type": "application/pdf"
        }
      ],
      "date": "",
      "classification": ""
    }
  ],
  "documents": [],
  "citations": [],
  "sources": [
    {
      "url": "https://www.legislature.ohio.gov/legislation/136/hb314",
      "note": ""
    },
    {
      "url": "https://search-prod.lis.state.oh.us/solarapi/v1/general_assembly_136//bills/hb314/",
      "note": ""
    }
  ],
  "extras": {},
  "jurisdiction": {
    "id": "ocd-jurisdiction/country:us/state:oh/government",
    "name": "Ohio",
    "classification": "state",
    "division_id": "ocd-division/country:us/state:oh"
  },
  "_processing": {
    "logs_latest_update": "2025-10-25T03:39:53Z",
    "text_extraction_latest_update": "2025-10-25T09:07:44.250061Z"
  }
}