{
  "legislative_session": "136",
  "identifier": "HB 478",
  "title": "Create jury tampering offense; revise court intimidation offenses",
  "from_organization": "~{\"classification\": \"lower\"}",
  "classification": [
    "bill"
  ],
  "subject": [
    "Courts",
    "Courts and Civil Law",
    "Crime and Punishment",
    "Crimes, Corrections, and Law Enforcement",
    "Public Officials and Employees",
    "State and Local Government"
  ],
  "abstracts": [],
  "other_titles": [
    {
      "note": "long title",
      "title": "To amend section 2921.04 and to enact section 2921.06 of the Revised Code to create the offense of jury tampering and to include a public servant in the offense of intimidation of an attorney, victim, witness, or public servant in a criminal case."
    }
  ],
  "other_identifiers": [],
  "actions": [
    {
      "description": "Introduced",
      "date": "2025-09-29",
      "organization_id": "~{\"classification\": \"lower\"}",
      "classification": [
        "introduction"
      ],
      "related_entities": [],
      "_processing": {
        "log_file_created": "2025-10-25T03:39:53Z"
      }
    },
    {
      "description": "Refer to Committee",
      "date": "2025-10-01",
      "organization_id": "~{\"classification\": \"lower\"}",
      "classification": [
        "referral-committee"
      ],
      "related_entities": [
        {
          "name": "House Judiciary Committee",
          "entity_type": "organization",
          "organization_id": null
        }
      ],
      "_processing": {
        "log_file_created": "2025-10-25T03:39:53Z"
      }
    }
  ],
  "sponsorships": [
    {
      "name": "David Thomas, D.",
      "classification": "primary",
      "entity_type": "person",
      "primary": true,
      "person_id": "~{\"name\": \"David Thomas, D.\"}",
      "organization_id": null
    },
    {
      "name": "Eric Synenberg",
      "classification": "primary",
      "entity_type": "person",
      "primary": true,
      "person_id": "~{\"name\": \"Eric Synenberg\"}",
      "organization_id": null
    },
    {
      "name": "Sean Brennan",
      "classification": "cosponsor",
      "entity_type": "person",
      "primary": false,
      "person_id": "~{\"name\": \"Sean Brennan\"}",
      "organization_id": null
    },
    {
      "name": "Gary Click",
      "classification": "cosponsor",
      "entity_type": "person",
      "primary": false,
      "person_id": "~{\"name\": \"Gary Click\"}",
      "organization_id": null
    },
    {
      "name": "Mark Hiner",
      "classification": "cosponsor",
      "entity_type": "person",
      "primary": false,
      "person_id": "~{\"name\": \"Mark Hiner\"}",
      "organization_id": null
    },
    {
      "name": "Mark Johnson",
      "classification": "cosponsor",
      "entity_type": "person",
      "primary": false,
      "person_id": "~{\"name\": \"Mark Johnson\"}",
      "organization_id": null
    },
    {
      "name": "Brian Lorenz",
      "classification": "cosponsor",
      "entity_type": "person",
      "primary": false,
      "person_id": "~{\"name\": \"Brian Lorenz\"}",
      "organization_id": null
    },
    {
      "name": "Kevin Miller, K.",
      "classification": "cosponsor",
      "entity_type": "person",
      "primary": false,
      "person_id": "~{\"name\": \"Kevin Miller, K.\"}",
      "organization_id": null
    },
    {
      "name": "Sharon Ray",
      "classification": "cosponsor",
      "entity_type": "person",
      "primary": false,
      "person_id": "~{\"name\": \"Sharon Ray\"}",
      "organization_id": null
    },
    {
      "name": "Terrence Upchurch",
      "classification": "cosponsor",
      "entity_type": "person",
      "primary": false,
      "person_id": "~{\"name\": \"Terrence Upchurch\"}",
      "organization_id": null
    }
  ],
  "related_bills": [],
  "versions": [
    {
      "note": "As Introduced",
      "links": [
        {
          "url": "https://search-prod.lis.state.oh.us/solarapi/v1/general_assembly_136/bills/hb478/IN/00/hb478_00_IN?format=pdf",
          "media_type": "application/pdf"
        }
      ],
      "date": "",
      "classification": ""
    }
  ],
  "documents": [],
  "citations": [],
  "sources": [
    {
      "url": "https://www.legislature.ohio.gov/legislation/136/hb478",
      "note": ""
    },
    {
      "url": "https://search-prod.lis.state.oh.us/solarapi/v1/general_assembly_136//bills/hb478/",
      "note": ""
    }
  ],
  "extras": {},
  "jurisdiction": {
    "id": "ocd-jurisdiction/country:us/state:oh/government",
    "name": "Ohio",
    "classification": "state",
    "division_id": "ocd-division/country:us/state:oh"
  },
  "_processing": {
    "logs_latest_update": "2025-10-25T03:39:53Z"
  }
}