{
  "legislative_session": "136",
  "identifier": "SB 297",
  "title": "Regards electric submetering companies and customers",
  "from_organization": "~{\"classification\": \"upper\"}",
  "classification": [
    "bill"
  ],
  "subject": [
    "Utilities"
  ],
  "abstracts": [],
  "other_titles": [
    {
      "note": "long title",
      "title": "To amend sections 4905.02 and 4928.53 and to enact sections 4933.51, 4933.52, 4933.53, 4933.54, 4933.55, 4933.57, and 4933.58 of the Revised Code to exempt electric submetering companies from classification as a public utility, to impose various requirements on such companies, and to extend eligibility for the percentage of income payment plan program to certain electric submetering company customers."
    }
  ],
  "other_identifiers": [],
  "actions": [
    {
      "description": "Introduced",
      "date": "2025-10-21",
      "organization_id": "~{\"classification\": \"upper\"}",
      "classification": [
        "introduction"
      ],
      "related_entities": [],
      "_processing": {
        "log_file_created": "2025-10-25T03:39:52Z"
      }
    },
    {
      "description": "Refer to Committee",
      "date": "2025-10-22",
      "organization_id": "~{\"classification\": \"upper\"}",
      "classification": [
        "referral-committee"
      ],
      "related_entities": [
        {
          "name": "Senate Public Utilities Committee",
          "entity_type": "organization",
          "organization_id": null
        }
      ],
      "_processing": {
        "log_file_created": "2025-10-25T03:39:52Z"
      }
    }
  ],
  "sponsorships": [
    {
      "name": "Hearcel Craig",
      "classification": "primary",
      "entity_type": "person",
      "primary": true,
      "person_id": "~{\"name\": \"Hearcel Craig\"}",
      "organization_id": null
    },
    {
      "name": "Kent Smith",
      "classification": "primary",
      "entity_type": "person",
      "primary": true,
      "person_id": "~{\"name\": \"Kent Smith\"}",
      "organization_id": null
    }
  ],
  "related_bills": [],
  "versions": [
    {
      "note": "As Introduced",
      "links": [
        {
          "url": "https://search-prod.lis.state.oh.us/solarapi/v1/general_assembly_136/bills/sb297/IN/00/sb297_00_IN?format=pdf",
          "media_type": "application/pdf"
        }
      ],
      "date": "",
      "classification": ""
    }
  ],
  "documents": [],
  "citations": [],
  "sources": [
    {
      "url": "https://www.legislature.ohio.gov/legislation/136/sb297",
      "note": ""
    },
    {
      "url": "https://search-prod.lis.state.oh.us/solarapi/v1/general_assembly_136//bills/sb297/",
      "note": ""
    }
  ],
  "extras": {},
  "jurisdiction": {
    "id": "ocd-jurisdiction/country:us/state:oh/government",
    "name": "Ohio",
    "classification": "state",
    "division_id": "ocd-division/country:us/state:oh"
  },
  "_processing": {
    "logs_latest_update": "2025-10-25T03:39:52Z",
    "text_extraction_latest_update": "2025-10-25T09:04:22.316630Z"
  }
}