{
  "legislative_session": "136",
  "identifier": "HB 257",
  "title": "Enact the Ohio Medical Debt Fairness Act",
  "from_organization": "~{\"classification\": \"lower\"}",
  "classification": [
    "bill"
  ],
  "subject": [
    "Commerce",
    "Commerce",
    "Consumer Finance",
    "Health and Human Services",
    "Public Health"
  ],
  "abstracts": [],
  "other_titles": [
    {
      "note": "long title",
      "title": "To amend sections 1343.01, 1343.03, 1349.01, 2716.02, 2716.03, and 4712.01 and to enact section 1349.54 of the Revised Code to limit the rate of interest on medical debt, to prohibit reporting medical debt to a consumer reporting agency, and to name this act the Ohio Medical Debt Fairness Act."
    }
  ],
  "other_identifiers": [],
  "actions": [
    {
      "description": "Introduced",
      "date": "2025-05-05",
      "organization_id": "~{\"classification\": \"lower\"}",
      "classification": [
        "introduction"
      ],
      "related_entities": [],
      "_processing": {
        "log_file_created": "2025-10-25T03:39:52Z"
      }
    },
    {
      "description": "Refer to Committee",
      "date": "2025-05-07",
      "organization_id": "~{\"classification\": \"lower\"}",
      "classification": [
        "referral-committee"
      ],
      "related_entities": [
        {
          "name": "House Health Committee",
          "entity_type": "organization",
          "organization_id": null
        }
      ],
      "_processing": {
        "log_file_created": "2025-10-25T03:39:52Z"
      }
    }
  ],
  "sponsorships": [
    {
      "name": "Michele Grim",
      "classification": "primary",
      "entity_type": "person",
      "primary": true,
      "person_id": "~{\"name\": \"Michele Grim\"}",
      "organization_id": null
    },
    {
      "name": "Jean Schmidt",
      "classification": "primary",
      "entity_type": "person",
      "primary": true,
      "person_id": "~{\"name\": \"Jean Schmidt\"}",
      "organization_id": null
    },
    {
      "name": "Juanita Brent",
      "classification": "cosponsor",
      "entity_type": "person",
      "primary": false,
      "person_id": "~{\"name\": \"Juanita Brent\"}",
      "organization_id": null
    },
    {
      "name": "Sean Brennan",
      "classification": "cosponsor",
      "entity_type": "person",
      "primary": false,
      "person_id": "~{\"name\": \"Sean Brennan\"}",
      "organization_id": null
    },
    {
      "name": "Beryl Piccolantonio",
      "classification": "cosponsor",
      "entity_type": "person",
      "primary": false,
      "person_id": "~{\"name\": \"Beryl Piccolantonio\"}",
      "organization_id": null
    },
    {
      "name": "Lauren McNally",
      "classification": "cosponsor",
      "entity_type": "person",
      "primary": false,
      "person_id": "~{\"name\": \"Lauren McNally\"}",
      "organization_id": null
    },
    {
      "name": "Tristan Rader",
      "classification": "cosponsor",
      "entity_type": "person",
      "primary": false,
      "person_id": "~{\"name\": \"Tristan Rader\"}",
      "organization_id": null
    },
    {
      "name": "Mark Sigrist",
      "classification": "cosponsor",
      "entity_type": "person",
      "primary": false,
      "person_id": "~{\"name\": \"Mark Sigrist\"}",
      "organization_id": null
    },
    {
      "name": "Crystal Lett",
      "classification": "cosponsor",
      "entity_type": "person",
      "primary": false,
      "person_id": "~{\"name\": \"Crystal Lett\"}",
      "organization_id": null
    },
    {
      "name": "Karen Brownlee",
      "classification": "cosponsor",
      "entity_type": "person",
      "primary": false,
      "person_id": "~{\"name\": \"Karen Brownlee\"}",
      "organization_id": null
    },
    {
      "name": "Ismail Mohamed",
      "classification": "cosponsor",
      "entity_type": "person",
      "primary": false,
      "person_id": "~{\"name\": \"Ismail Mohamed\"}",
      "organization_id": null
    },
    {
      "name": "C. Russo",
      "classification": "cosponsor",
      "entity_type": "person",
      "primary": false,
      "person_id": "~{\"name\": \"C. Russo\"}",
      "organization_id": null
    },
    {
      "name": "Sedrick Denson",
      "classification": "cosponsor",
      "entity_type": "person",
      "primary": false,
      "person_id": "~{\"name\": \"Sedrick Denson\"}",
      "organization_id": null
    },
    {
      "name": "Christine Cockley",
      "classification": "cosponsor",
      "entity_type": "person",
      "primary": false,
      "person_id": "~{\"name\": \"Christine Cockley\"}",
      "organization_id": null
    },
    {
      "name": "Anita Somani",
      "classification": "cosponsor",
      "entity_type": "person",
      "primary": false,
      "person_id": "~{\"name\": \"Anita Somani\"}",
      "organization_id": null
    },
    {
      "name": "Mark Johnson",
      "classification": "cosponsor",
      "entity_type": "person",
      "primary": false,
      "person_id": "~{\"name\": \"Mark Johnson\"}",
      "organization_id": null
    },
    {
      "name": "Dontavius Jarrells",
      "classification": "cosponsor",
      "entity_type": "person",
      "primary": false,
      "person_id": "~{\"name\": \"Dontavius Jarrells\"}",
      "organization_id": null
    },
    {
      "name": "Terrence Upchurch",
      "classification": "cosponsor",
      "entity_type": "person",
      "primary": false,
      "person_id": "~{\"name\": \"Terrence Upchurch\"}",
      "organization_id": null
    },
    {
      "name": "Derrick Hall, D.",
      "classification": "cosponsor",
      "entity_type": "person",
      "primary": false,
      "person_id": "~{\"name\": \"Derrick Hall, D.\"}",
      "organization_id": null
    },
    {
      "name": "Rachel Baker",
      "classification": "cosponsor",
      "entity_type": "person",
      "primary": false,
      "person_id": "~{\"name\": \"Rachel Baker\"}",
      "organization_id": null
    },
    {
      "name": "Veronica Sims",
      "classification": "cosponsor",
      "entity_type": "person",
      "primary": false,
      "person_id": "~{\"name\": \"Veronica Sims\"}",
      "organization_id": null
    },
    {
      "name": "Munira Abdullahi",
      "classification": "cosponsor",
      "entity_type": "person",
      "primary": false,
      "person_id": "~{\"name\": \"Munira Abdullahi\"}",
      "organization_id": null
    },
    {
      "name": "Eric Synenberg",
      "classification": "cosponsor",
      "entity_type": "person",
      "primary": false,
      "person_id": "~{\"name\": \"Eric Synenberg\"}",
      "organization_id": null
    },
    {
      "name": "Joseph Miller, J.",
      "classification": "cosponsor",
      "entity_type": "person",
      "primary": false,
      "person_id": "~{\"name\": \"Joseph Miller, J.\"}",
      "organization_id": null
    },
    {
      "name": "Phillip Robinson",
      "classification": "cosponsor",
      "entity_type": "person",
      "primary": false,
      "person_id": "~{\"name\": \"Phillip Robinson\"}",
      "organization_id": null
    },
    {
      "name": "Tracy Richardson",
      "classification": "cosponsor",
      "entity_type": "person",
      "primary": false,
      "person_id": "~{\"name\": \"Tracy Richardson\"}",
      "organization_id": null
    },
    {
      "name": "Monica Robb Blasdel",
      "classification": "cosponsor",
      "entity_type": "person",
      "primary": false,
      "person_id": "~{\"name\": \"Monica Robb Blasdel\"}",
      "organization_id": null
    },
    {
      "name": "Thomas Hall, T.",
      "classification": "cosponsor",
      "entity_type": "person",
      "primary": false,
      "person_id": "~{\"name\": \"Thomas Hall, T.\"}",
      "organization_id": null
    }
  ],
  "related_bills": [],
  "versions": [
    {
      "note": "As Introduced",
      "links": [
        {
          "url": "https://search-prod.lis.state.oh.us/solarapi/v1/general_assembly_136/bills/hb257/IN/00/hb257_00_IN?format=pdf",
          "media_type": "application/pdf"
        }
      ],
      "date": "",
      "classification": ""
    }
  ],
  "documents": [],
  "citations": [],
  "sources": [
    {
      "url": "https://www.legislature.ohio.gov/legislation/136/hb257",
      "note": ""
    },
    {
      "url": "https://search-prod.lis.state.oh.us/solarapi/v1/general_assembly_136//bills/hb257/",
      "note": ""
    }
  ],
  "extras": {},
  "jurisdiction": {
    "id": "ocd-jurisdiction/country:us/state:oh/government",
    "name": "Ohio",
    "classification": "state",
    "division_id": "ocd-division/country:us/state:oh"
  },
  "_processing": {
    "logs_latest_update": "2025-10-25T03:39:52Z"
  }
}