{
  "legislative_session": "136",
  "identifier": "HB 519",
  "title": "Prohibit specified actions with intent to steal a motor vehicle",
  "from_organization": "~{\"classification\": \"lower\"}",
  "classification": [
    "bill"
  ],
  "subject": [
    "Crime and Punishment",
    "Crimes, Corrections, and Law Enforcement",
    "Crimes, Corrections, and Law Enforcement"
  ],
  "abstracts": [],
  "other_titles": [
    {
      "note": "long title",
      "title": "To amend section 2923.24 of the Revised Code to prohibit possession of an electronic device under circumstances indicating an intent to steal a motor vehicle."
    }
  ],
  "other_identifiers": [],
  "actions": [
    {
      "description": "Introduced",
      "date": "2025-10-14",
      "organization_id": "~{\"classification\": \"lower\"}",
      "classification": [
        "introduction"
      ],
      "related_entities": [],
      "_processing": {
        "log_file_created": "2025-10-25T03:39:53Z"
      }
    },
    {
      "description": "Refer to Committee",
      "date": "2025-10-15",
      "organization_id": "~{\"classification\": \"lower\"}",
      "classification": [
        "referral-committee"
      ],
      "related_entities": [
        {
          "name": "House Public Safety Committee",
          "entity_type": "organization",
          "organization_id": null
        }
      ],
      "_processing": {
        "log_file_created": "2025-10-25T03:39:53Z"
      }
    }
  ],
  "sponsorships": [
    {
      "name": "Andrea White, A.",
      "classification": "primary",
      "entity_type": "person",
      "primary": true,
      "person_id": "~{\"name\": \"Andrea White, A.\"}",
      "organization_id": null
    }
  ],
  "related_bills": [],
  "versions": [
    {
      "note": "As Introduced",
      "links": [
        {
          "url": "https://search-prod.lis.state.oh.us/solarapi/v1/general_assembly_136/bills/hb519/IN/00/hb519_00_IN?format=pdf",
          "media_type": "application/pdf"
        }
      ],
      "date": "",
      "classification": ""
    }
  ],
  "documents": [],
  "citations": [],
  "sources": [
    {
      "url": "https://www.legislature.ohio.gov/legislation/136/hb519",
      "note": ""
    },
    {
      "url": "https://search-prod.lis.state.oh.us/solarapi/v1/general_assembly_136//bills/hb519/",
      "note": ""
    }
  ],
  "extras": {},
  "jurisdiction": {
    "id": "ocd-jurisdiction/country:us/state:oh/government",
    "name": "Ohio",
    "classification": "state",
    "division_id": "ocd-division/country:us/state:oh"
  },
  "_processing": {
    "logs_latest_update": "2025-10-25T03:39:53Z",
    "text_extraction_latest_update": "2025-10-25T09:19:02.989722Z"
  }
}