{
  "legislative_session": "136",
  "identifier": "SB 260",
  "title": "Enact the Voter Registration Modernization Act",
  "from_organization": "~{\"classification\": \"upper\"}",
  "classification": [
    "bill"
  ],
  "subject": [
    "Elections"
  ],
  "abstracts": [],
  "other_titles": [
    {
      "note": "long title",
      "title": "To amend sections 3501.01, 3503.09, 3503.10, 3503.11, 3503.14, 3503.15, 3503.153, 3503.16, 3503.19, 3503.20, 3503.23, 3503.28, 3505.181, 3509.02, 3509.03, 3509.04, 3509.08, 3513.041, 3513.05, 3513.07, 3513.18, 3513.19, 3513.191, 3513.257, 3517.012, 3517.013, and 3599.12; to enact section 3503.071; and to repeal section 3513.20 of the Revised Code to permit an elector to change party affiliation through the voter registration process and to name this act the Voter Registration Modernization Act."
    }
  ],
  "other_identifiers": [],
  "actions": [
    {
      "description": "Introduced",
      "date": "2025-09-16",
      "organization_id": "~{\"classification\": \"upper\"}",
      "classification": [
        "introduction"
      ],
      "related_entities": [],
      "_processing": {
        "log_file_created": "2025-10-25T03:39:53Z"
      }
    },
    {
      "description": "Refer to Committee",
      "date": "2025-10-01",
      "organization_id": "~{\"classification\": \"upper\"}",
      "classification": [
        "referral-committee"
      ],
      "related_entities": [
        {
          "name": "Senate General Government Committee",
          "entity_type": "organization",
          "organization_id": null
        }
      ],
      "_processing": {
        "log_file_created": "2025-10-25T03:39:53Z"
      }
    }
  ],
  "sponsorships": [
    {
      "name": "Michele Reynolds",
      "classification": "primary",
      "entity_type": "person",
      "primary": true,
      "person_id": "~{\"name\": \"Michele Reynolds\"}",
      "organization_id": null
    }
  ],
  "related_bills": [],
  "versions": [
    {
      "note": "As Introduced",
      "links": [
        {
          "url": "https://search-prod.lis.state.oh.us/solarapi/v1/general_assembly_136/bills/sb260/IN/00/sb260_00_IN?format=pdf",
          "media_type": "application/pdf"
        }
      ],
      "date": "",
      "classification": ""
    }
  ],
  "documents": [],
  "citations": [],
  "sources": [
    {
      "url": "https://www.legislature.ohio.gov/legislation/136/sb260",
      "note": ""
    },
    {
      "url": "https://search-prod.lis.state.oh.us/solarapi/v1/general_assembly_136//bills/sb260/",
      "note": ""
    }
  ],
  "extras": {},
  "jurisdiction": {
    "id": "ocd-jurisdiction/country:us/state:oh/government",
    "name": "Ohio",
    "classification": "state",
    "division_id": "ocd-division/country:us/state:oh"
  },
  "_processing": {
    "logs_latest_update": "2025-10-25T03:39:53Z"
  }
}